.gitignore
LICENSE
README.md
pyproject.toml
setup.py
.github/workflows/python-publish.yml
src/barecat_cython/__init__.py
src/barecat_cython/_version.py
src/barecat_cython/barecat.c
src/barecat_cython/barecat.h
src/barecat_cython/barecat_cython.pyx
src/barecat_cython/barecat_mmap.c
src/barecat_cython/barecat_mmap.h
src/barecat_cython/crc32c.c
src/barecat_cython/crc32c.h
src/barecat_cython.egg-info/PKG-INFO
src/barecat_cython.egg-info/SOURCES.txt
src/barecat_cython.egg-info/dependency_links.txt
src/barecat_cython.egg-info/requires.txt
src/barecat_cython.egg-info/top_level.txt