Metadata-Version: 2.4
Name: barecat-cython
Version: 0.0.2
Summary: Cython-based implementation of the Barecat archive format.
Author-email: István Sárándi <istvan.sarandi@gmail.com>
License-Expression: MIT
Project-URL: Homepage, https://github.com/isarandi/barecat-cython
Project-URL: Repository, https://github.com/isarandi/barecat-cython
Project-URL: Issues, https://github.com/isarandi/barecat-cython/issues
Project-URL: Author, https://istvansarandi.com
Keywords: sqlite,dataset,storage,archive,random-access,image-dataset,filesystem,key-value-store,deep-learning,data-loader,file-indexing
Classifier: Development Status :: 4 - Beta
Classifier: Intended Audience :: Developers
Classifier: Intended Audience :: Science/Research
Classifier: Topic :: Scientific/Engineering :: Information Analysis
Classifier: Topic :: Software Development :: Libraries
Classifier: Topic :: System :: Archiving
Classifier: Topic :: System :: Filesystems
Classifier: Programming Language :: Python
Classifier: Programming Language :: Python :: 3
Classifier: Programming Language :: Cython
Classifier: Operating System :: POSIX :: Linux
Requires-Python: >=3.9
License-File: LICENSE
Requires-Dist: numpy
Dynamic: license-file
